getpathfromreg/LICENSE
getpathfromreg/README.MD
getpathfromreg/__init__.py
getpathfromreg/requirements.txt
getpathfromreg/thirdparty.json
getpathfromreg-0.12.dist-info/LICENSE.rst
getpathfromreg-0.12.dist-info/METADATA
getpathfromreg-0.12.dist-info/WHEEL
getpathfromreg-0.12.dist-info/top_level.txt
getpathfromreg-0.12.dist-info/RECORD
